{
  "$schema": "https://developer.microsoft.com/json-schemas/spfx/client-side-web-part-manifest.schema.json",
  "id": "d8376353-c68b-45de-bbe3-67ee47059cc7",
  "alias": "UniversalAppLauncherWebPart",
  "componentType": "WebPart",

  // The "*" signifies that the version should be taken from the package.json
  "version": "*",
  "manifestVersion": 2,

  // If true, the component can only be installed on sites where Custom Script is allowed.
  // Components that allow authors to embed arbitrary script code should set this to true.
  // https://support.office.com/en-us/article/Turn-scripting-capabilities-on-or-off-1f2c515f-5d7e-448a-9fd7-835da935584f
  "requiresCustomScript": false,
  "supportedHosts": ["SharePointWebPart", "SharePointFullPage"],
  "supportsThemeVariants": true,

  "preconfiguredEntries": [{
    "groupId": "5c03119e-3074-46fd-976b-c60198311f70", // Advanced
    "group": { "default": "Advanced" },
    "title": { "default": "Lanzador universal de accesos" },
    "description": { "default": "Muestra un grid configurable de accesos a apps, sites, formularios y utilidades corporativas." },
    "officeFabricIconFontName": "Page",
    "properties": {
      "title": "Lanzador universal de accesos",
      "subtitle": "Muestra un grid configurable de accesos a apps, sites, formularios y utilidades corporativas.",
      "audienceMode": "group",
      "currentAudienceTokens": "general",
      "defaultCategory": "All",
      "maxItems": 8,
      "openInNewTab": false,
      "launchItemsJson": "[{\"id\":\"portal-general\",\"title\":\"Portal general\",\"category\":\"General\",\"audienceTokens\":[\"general\",\"all\"],\"description\":\"Entrada genérica a recursos corporativos de uso común.\",\"iconName\":\"Page\",\"priority\":1,\"featured\":true,\"openUrl\":\"/sites/home\"},{\"id\":\"portal-people\",\"title\":\"Portal Personas\",\"category\":\"RRHH\",\"audienceTokens\":[\"people\",\"hr\"],\"description\":\"Acceso a políticas, incidencias y formularios del equipo de personas.\",\"iconName\":\"Contact\",\"priority\":2,\"featured\":true,\"openUrl\":\"/sites/hr\"}]"
    }
  }]
}
